odoo/addons/product_name_with_country/README.rst
odoo/addons/product_name_with_country/__init__.py
odoo/addons/product_name_with_country/__manifest__.py
odoo/addons/product_name_with_country/i18n/es.po
odoo/addons/product_name_with_country/models/__init__.py
odoo/addons/product_name_with_country/models/product_template.py
odoo/addons/product_name_with_country/static/description/icon.png
odoo/addons/product_name_with_country/views/product_template_views.xml
odoo14_addon_product_name_with_country-14.0.1.0.3.dist-info/METADATA
odoo14_addon_product_name_with_country-14.0.1.0.3.dist-info/WHEEL
odoo14_addon_product_name_with_country-14.0.1.0.3.dist-info/top_level.txt
odoo14_addon_product_name_with_country-14.0.1.0.3.dist-info/RECORD
